{
  "id": "2026-03-week5",
  "title": "🏕️ 캠핑장 운영 뉴스레터 - 2026년 3월 5주차",
  "week_info": {
    "year": 2026,
    "month": 3,
    "week": 14,
    "week_of_month": 5,
    "date": "2026-03-30",
    "display": "2026년 3월 5주차"
  },
  "created_at": "2026-03-30T01:30:10.729354",
  "items": [
    {
      "title": "객실 미온수 수영장 노천탕 연매출 3억 프라이빗 입지 (24-0662)",
      "url": "https://blog.naver.com/pension114_com/224232611759",
      "source": "네이버 블로그",
      "description": "연매출 3억 ⦁ 바닷가 바로 앞, 부산 53분, 통영IC 38분 ⦁ 펜션/캠핑장 전문 《펜션114》 1. 소재지... 주변 관광지 ⦁ 와현모래숲해변: 펜션에서 약 28분 (약 20.3km), 깨끗한 모래사장이 특징인 해수욕장...",
      "published_date": "2026-03-28T00:00:00",
      "category": "블로그",
      "score": 0.0
    },
    {
      "title": "Weekly Logistics News Letter Vol.782(3/27)",
      "url": "https://blog.naver.com/acesu/224231394562",
      "source": "네이버 블로그",
      "description": "강화..운영 안정성도 개선 l 전쟁부터 물류 마비까지…하겐 호이바흐 SAP CMO &quot;공급망 위기, l 디젤값... l 캠핑장도 산속도 '드론 배송'…안양시, 미래형 물류 현실화한다 l 엑소텍, ‘2026...",
      "published_date": "2026-03-27T00:00:00",
      "category": "블로그",
      "score": 0.0
    },
    {
      "title": "사회 1*헤드라인.사건사고.교육.노동.언론.환경=네이버...",
      "url": "https://blog.naver.com/c1c1b1b1/224229781350",
      "source": "네이버 블로그",
      "description": "마약을 하려고 캠핑장에 가족만 남겨두고 혼자 집으로 달려온 적도 있어요.” 마약 사범 ‘워라밸’이 마약의 수렁에 빠진 건 고작 8개월 남짓이었다. 이 8개월이 조선일보 3시간전 [어떻게 생각하십니까]...",
      "published_date": "2026-03-26T00:00:00",
      "category": "블로그",
      "score": 0.0
    },
    {
      "title": "떠나요 파트너센터 홈페이지 바로가기 안내",
      "url": "https://blog.naver.com/junior6101/224229537418",
      "source": "네이버 블로그",
      "description": "떠나요 파트너센터는 펜션, 호텔, 게스트하우스, 캠핑장 등 다양한 숙박 시설 운영자들을 위해 맞춤 설계된 플랫폼입니다. 이 시스템을 통해 사장님들은 예약 관리, 실시간 객실 현황 업데이트, 매출 분석...",
      "published_date": "2026-03-26T00:00:00",
      "category": "블로그",
      "score": 0.0
    },
    {
      "title": "네이버 플레이스 새로오픈 신청하는 방법",
      "url": "https://blog.naver.com/heeok8710/224229303128",
      "source": "네이버 블로그",
      "description": "오늘은 자영업을 운영하시는 많은 사장님들께서 궁금해 하시는 플레이스 새로오픈 신청에 대해 자세히... 신청 가능한 업종은 게스트하우스, 캠핑장, 전통숙소, 민박, 펜션, 여관, 미용실, 네일샵, 음식점 등이...",
      "published_date": "2026-03-25T00:00:00",
      "category": "블로그",
      "score": 0.0
    },
    {
      "title": "예약률을 바꾸는 캠핑장 마케팅이 중요한 이유?",
      "url": "https://blog.naver.com/she2847/224230556313",
      "source": "네이버 블로그",
      "description": "좋은 방법입니다. 3. 후기 관리 요즘 소비자들은 광고보다 실제 이용자의 경험을 더 신뢰합니다. 실제로... 높이는 방식도 뛰어납니다. 4. 커뮤니티 활용 특히 가족 단위 고객을 타깃으로 한다면 맘카페 및 캠핑장...",
      "published_date": "2026-03-26T00:00:00",
      "category": "블로그",
      "score": 0.0
    },
    {
      "title": "서울대공원 캠핑장 예약 성공을 위한 3가지 필승 전략",
      "url": "https://blog.naver.com/tripgenius/224231236929",
      "source": "네이버 블로그",
      "description": "서울대공원 캠핑장은 접근성이 뛰어나고 시설이 잘 갖춰져 있어 경쟁이 매우 치열하지만 몇 가지 핵심... 입장료 주차비 및 필수 준비물 체크리스트 캠핑을 더욱 완벽하게 즐기기 위해서는 비용 체계와...",
      "published_date": "2026-03-27T00:00:00",
      "category": "블로그",
      "score": 0.0
    },
    {
      "title": "에어텐트 자가 수리, 이럴 땐 전문가에게! A/S 및 수리 업체...",
      "url": "https://blog.naver.com/moneypom/224230730735",
      "source": "네이버 블로그",
      "description": "캠핑을 사랑하는 여러분, 혹시 즐거운 캠핑장에서 에어텐트가 서서히 주저앉는 아찔한 경험을 해보신 적 있나요? ⛺ 저도 작년 가을, 야심 차게 준비한 캠핑 첫날 밤에 에어빔이 미세하게 새는 바람에 밤새...",
      "published_date": "2026-03-26T00:00:00",
      "category": "블로그",
      "score": 0.0
    },
    {
      "title": "가평 청소일자리 시작 전 알아둘 핵심",
      "url": "https://blog.naver.com/sebw9480/224207655696",
      "source": "네이버 블로그",
      "description": "정리, 캠핑장 샤워실 관리, 아파트 공용부 미화처럼 형태가 나뉘죠. 주말·성수기만 집중하는 단기형도... 그래서 현장에서는 작업 표준과 체크리스트를 쓰는 곳이 늘었어요. 가평은 관광·레저 비중이 있어서...",
      "published_date": "2026-03-26T00:00:00",
      "category": "블로그",
      "score": 0.0
    },
    {
      "title": "캠핑장 창업 준비부터 수익까지현실적인 완전 가이드",
      "url": "https://blog.naver.com/hwarim701/224227109112",
      "source": "네이버 블로그",
      "description": "원 성수기(4~6월, 9~11월)와 비수기(1~2월) 매출 차이가 2~3배 이상. 연간 매출 기준으로 안정적인 수익을 판단하는 것이 중요합니다. ✅ 캠핑장 창업 실패를 줄이는 핵심 체크리스트 수많은 캠핑장 창업 실패...",
      "published_date": "2026-03-23T00:00:00",
      "category": "블로그",
      "score": 0.0
    }
  ],
  "items_count": 10
}